hubu/__init__.py
hubu/base.py
hubu/bucket_client.py
hubu/download_manager.py
hubu/downloadable.py
hubu/downloader.py
hubu/humble_bundle.py
hubu/main.py
hubu-1.0.5.dist-info/LICENSE
hubu-1.0.5.dist-info/METADATA
hubu-1.0.5.dist-info/WHEEL
hubu-1.0.5.dist-info/entry_points.txt
hubu-1.0.5.dist-info/top_level.txt
hubu-1.0.5.dist-info/zip-safe
hubu-1.0.5.dist-info/RECORD
